sinner/NeuralNetwork.py
sinner/__init__.py
sinner-0.0.1.dist-info/LICENSE
sinner-0.0.1.dist-info/METADATA
sinner-0.0.1.dist-info/WHEEL
sinner-0.0.1.dist-info/top_level.txt
sinner-0.0.1.dist-info/RECORD
