Metadata-Version: 2.1
Name: sinner
Version: 0.0.1
Summary: SINNER - Simplest Implementation of Neural Networks for Effortless Runs
Home-page: https://github.com/friarhob/sinner-neural
Author: Friar Hob
Author-email: github@friarhob.33mail.com
License: UNKNOWN
Platform: UNKNOWN
Classifier: Programming Language :: Python :: 3
Classifier: License :: OSI Approved :: MIT License
Classifier: Operating System :: OS Independent
Requires-Python: >=3.6
